LICENSE
README.md
setup.py
ttxt/__init__.py
ttxt.egg-info/PKG-INFO
ttxt.egg-info/SOURCES.txt
ttxt.egg-info/dependency_links.txt
ttxt.egg-info/top_level.txt
ttxt/base/__init__.py
ttxt/base/baseFuturesExchange.py
ttxt/base/baseSpotExchange.py
ttxt/exchanges/__init__.py
ttxt/exchanges/ascendex.py
ttxt/exchanges/biconomy.py
ttxt/exchanges/binance.py
ttxt/exchanges/bingx.py
ttxt/exchanges/bitget.py
ttxt/exchanges/bitgetFutures.py
ttxt/exchanges/bitmart.py
ttxt/exchanges/blofin.py
ttxt/exchanges/bybit.py
ttxt/exchanges/bybitFutures.py
ttxt/exchanges/coinbase.py
ttxt/exchanges/coindcx.py
ttxt/exchanges/coinlist.py
ttxt/exchanges/coinstore.py
ttxt/exchanges/cryptocom.py
ttxt/exchanges/gateFutures.py
ttxt/exchanges/gateio.py
ttxt/exchanges/huobi.py
ttxt/exchanges/kraken.py
ttxt/exchanges/kucoin.py
ttxt/exchanges/mexc.py
ttxt/exchanges/okx.py
ttxt/exchanges/whitebit.py
ttxt/exchanges/xt.py
ttxt/tests/__init__.py
ttxt/tests/testExchange.py
ttxt/types/__init__.py
ttxt/types/baseTypes.py
ttxt/utils/__init__.py
ttxt/utils/general.py
ttxt/utils/xtUtils.py