Metadata-Version: 2.1
Name: ttxt
Version: 0.0.7.3
Summary: TT exchange interfacing library
Author: sus
License-File: LICENSE
